{
  "annotations": {
    "list": [
      {
        "builtIn": 1,
        "datasource": { "type": "grafana", "uid": "-- Grafana --" },
        "enable": true,
        "hide": true,
        "iconColor": "rgba(0, 211, 255, 1)",
        "name": "Annotations & Alerts",
        "type": "dashboard"
      }
    ]
  },
  "editable": true,
  "fiscalYearStartMonth": 0,
  "graphTooltip": 1,
  "id": null,
  "links": [],
  "panels": [
    {
      "collapsed": false,
      "gridPos": { "h": 1, "w": 24, "x": 0, "y": 0 },
      "id": 1,
      "title": "Service Health",
      "type": "row"
    },
    {
      "datasource": { "type": "prometheus", "uid": "prometheus" },
      "description": "Up/Down status for all ParkirPintar services based on recent span activity",
      "fieldConfig": {
        "defaults": {
          "color": { "mode": "thresholds" },
          "mappings": [
            { "options": { "0": { "color": "red", "text": "DOWN" }, "1": { "color": "green", "text": "UP" } }, "type": "value" }
          ],
          "thresholds": {
            "mode": "absolute",
            "steps": [
              { "color": "red", "value": null },
              { "color": "green", "value": 1 }
            ]
          }
        },
        "overrides": []
      },
      "gridPos": { "h": 4, "w": 24, "x": 0, "y": 1 },
      "id": 2,
      "options": {
        "colorMode": "background",
        "graphMode": "none",
        "justifyMode": "auto",
        "orientation": "horizontal",
        "reduceOptions": { "calcs": ["lastNotNull"], "fields": "", "values": false },
        "textMode": "auto"
      },
      "title": "Service Health",
      "type": "stat",
      "targets": [
        {
          "datasource": { "type": "prometheus", "uid": "prometheus" },
          "expr": "clamp_max(sum(rate(traces_spanmetrics_calls_total{service_name=\"parkir-pintar-gateway\"}[5m])), 1) or vector(0)",
          "legendFormat": "Gateway",
          "refId": "A"
        },
        {
          "datasource": { "type": "prometheus", "uid": "prometheus" },
          "expr": "clamp_max(sum(rate(traces_spanmetrics_calls_total{service_name=\"parkir-pintar-reservation\"}[5m])), 1) or vector(0)",
          "legendFormat": "Reservation",
          "refId": "B"
        },
        {
          "datasource": { "type": "prometheus", "uid": "prometheus" },
          "expr": "clamp_max(sum(rate(traces_spanmetrics_calls_total{service_name=\"parkir-pintar-payment\"}[5m])), 1) or vector(0)",
          "legendFormat": "Payment",
          "refId": "C"
        },
        {
          "datasource": { "type": "prometheus", "uid": "prometheus" },
          "expr": "clamp_max(sum(rate(traces_spanmetrics_calls_total{service_name=\"parkir-pintar-billing\"}[5m])), 1) or vector(0)",
          "legendFormat": "Billing",
          "refId": "D"
        },
        {
          "datasource": { "type": "prometheus", "uid": "prometheus" },
          "expr": "clamp_max(sum(rate(traces_spanmetrics_calls_total{service_name=\"parkir-pintar-presence\"}[5m])), 1) or vector(0)",
          "legendFormat": "Presence",
          "refId": "E"
        },
        {
          "datasource": { "type": "prometheus", "uid": "prometheus" },
          "expr": "clamp_max(sum(rate(traces_spanmetrics_calls_total{service_name=\"parkir-pintar-notification\"}[5m])), 1) or vector(0)",
          "legendFormat": "Notification",
          "refId": "F"
        },
        {
          "datasource": { "type": "prometheus", "uid": "prometheus" },
          "expr": "clamp_max(sum(rate(traces_spanmetrics_calls_total{service_name=\"parkir-pintar-search\"}[5m])), 1) or vector(0)",
          "legendFormat": "Search",
          "refId": "G"
        }
      ]
    },
    {
      "collapsed": false,
      "gridPos": { "h": 1, "w": 24, "x": 0, "y": 5 },
      "id": 3,
      "title": "RED Metrics",
      "type": "row"
    },
    {
      "datasource": { "type": "prometheus", "uid": "prometheus" },
      "description": "HTTP and gRPC request rate per service",
      "fieldConfig": {
        "defaults": {
          "color": { "mode": "palette-classic" },
          "custom": {
            "axisBorderShow": false,
            "axisCenteredZero": false,
            "axisColorMode": "text",
            "axisLabel": "",
            "axisPlacement": "auto",
            "barAlignment": 0,
            "drawStyle": "line",
            "fillOpacity": 15,
            "gradientMode": "none",
            "hideFrom": { "legend": false, "tooltip": false, "viz": false },
            "insertNulls": false,
            "lineInterpolation": "smooth",
            "lineWidth": 2,
            "pointSize": 5,
            "scaleDistribution": { "type": "linear" },
            "showPoints": "never",
            "spanNulls": false,
            "stacking": { "group": "A", "mode": "none" },
            "thresholdsStyle": { "mode": "off" }
          },
          "mappings": [],
          "thresholds": {
            "mode": "absolute",
            "steps": [
              { "color": "green", "value": null },
              { "color": "red", "value": 80 }
            ]
          },
          "unit": "reqps"
        },
        "overrides": []
      },
      "gridPos": { "h": 8, "w": 8, "x": 0, "y": 6 },
      "id": 4,
      "options": {
        "legend": { "calcs": ["mean", "lastNotNull"], "displayMode": "table", "placement": "bottom", "showLegend": true },
        "tooltip": { "mode": "multi", "sort": "desc" }
      },
      "title": "Request Rate (HTTP + gRPC)",
      "type": "timeseries",
      "targets": [
        {
          "datasource": { "type": "prometheus", "uid": "prometheus" },
          "expr": "sum(rate(http_requests_total[5m])) by (job)",
          "legendFormat": "HTTP {{job}}",
          "refId": "A"
        },
        {
          "datasource": { "type": "prometheus", "uid": "prometheus" },
          "expr": "sum(rate(grpc_requests_total[5m])) by (job)",
          "legendFormat": "gRPC {{job}}",
          "refId": "B"
        },
        {
          "datasource": { "type": "prometheus", "uid": "prometheus" },
          "expr": "sum(rate(traces_spanmetrics_calls_total{span_kind=\"SPAN_KIND_SERVER\"}[5m])) by (service_name)",
          "legendFormat": "spans {{service_name}}",
          "refId": "C"
        }
      ]
    },
    {
      "datasource": { "type": "prometheus", "uid": "prometheus" },
      "description": "Error rates: HTTP 4xx, 5xx, and gRPC non-OK",
      "fieldConfig": {
        "defaults": {
          "color": { "mode": "palette-classic" },
          "custom": {
            "axisBorderShow": false,
            "axisCenteredZero": false,
            "axisColorMode": "text",
            "axisLabel": "",
            "axisPlacement": "auto",
            "barAlignment": 0,
            "drawStyle": "line",
            "fillOpacity": 15,
            "gradientMode": "none",
            "hideFrom": { "legend": false, "tooltip": false, "viz": false },
            "insertNulls": false,
            "lineInterpolation": "smooth",
            "lineWidth": 2,
            "pointSize": 5,
            "scaleDistribution": { "type": "linear" },
            "showPoints": "never",
            "spanNulls": false,
            "stacking": { "group": "A", "mode": "none" },
            "thresholdsStyle": { "mode": "off" }
          },
          "mappings": [],
          "thresholds": {
            "mode": "absolute",
            "steps": [
              { "color": "green", "value": null },
              { "color": "red", "value": 0.05 }
            ]
          },
          "unit": "reqps"
        },
        "overrides": []
      },
      "gridPos": { "h": 8, "w": 8, "x": 8, "y": 6 },
      "id": 5,
      "options": {
        "legend": { "calcs": ["mean", "lastNotNull"], "displayMode": "table", "placement": "bottom", "showLegend": true },
        "tooltip": { "mode": "multi", "sort": "desc" }
      },
      "title": "Error Rate (4xx / 5xx / gRPC)",
      "type": "timeseries",
      "targets": [
        {
          "datasource": { "type": "prometheus", "uid": "prometheus" },
          "expr": "sum(rate(http_requests_total{status_code=~\"4..\"}[5m])) by (job)",
          "legendFormat": "4xx {{job}}",
          "refId": "A"
        },
        {
          "datasource": { "type": "prometheus", "uid": "prometheus" },
          "expr": "sum(rate(http_requests_total{status_code=~\"5..\"}[5m])) by (job)",
          "legendFormat": "5xx {{job}}",
          "refId": "B"
        },
        {
          "datasource": { "type": "prometheus", "uid": "prometheus" },
          "expr": "sum(rate(grpc_requests_total{grpc_code!=\"OK\"}[5m])) by (job)",
          "legendFormat": "gRPC err {{job}}",
          "refId": "C"
        },
        {
          "datasource": { "type": "prometheus", "uid": "prometheus" },
          "expr": "sum(rate(traces_spanmetrics_calls_total{status_code=\"STATUS_CODE_ERROR\"}[5m])) by (service_name)",
          "legendFormat": "span err {{service_name}}",
          "refId": "D"
        }
      ]
    },
    {
      "datasource": { "type": "prometheus", "uid": "prometheus" },
      "description": "Latency percentiles P50, P95, P99 across services",
      "fieldConfig": {
        "defaults": {
          "color": { "mode": "palette-classic" },
          "custom": {
            "axisBorderShow": false,
            "axisCenteredZero": false,
            "axisColorMode": "text",
            "axisLabel": "",
            "axisPlacement": "auto",
            "barAlignment": 0,
            "drawStyle": "line",
            "fillOpacity": 10,
            "gradientMode": "none",
            "hideFrom": { "legend": false, "tooltip": false, "viz": false },
            "insertNulls": false,
            "lineInterpolation": "smooth",
            "lineWidth": 2,
            "pointSize": 5,
            "scaleDistribution": { "type": "linear" },
            "showPoints": "never",
            "spanNulls": false,
            "stacking": { "group": "A", "mode": "none" },
            "thresholdsStyle": { "mode": "off" }
          },
          "mappings": [],
          "thresholds": {
            "mode": "absolute",
            "steps": [
              { "color": "green", "value": null },
              { "color": "yellow", "value": 250 },
              { "color": "red", "value": 500 }
            ]
          },
          "unit": "ms"
        },
        "overrides": []
      },
      "gridPos": { "h": 8, "w": 8, "x": 16, "y": 6 },
      "id": 6,
      "options": {
        "legend": { "calcs": ["mean", "lastNotNull"], "displayMode": "table", "placement": "bottom", "showLegend": true },
        "tooltip": { "mode": "multi", "sort": "desc" }
      },
      "title": "Latency Percentiles (P50 / P95 / P99)",
      "type": "timeseries",
      "targets": [
        {
          "datasource": { "type": "prometheus", "uid": "prometheus" },
          "expr": "histogram_quantile(0.50, sum(rate(traces_spanmetrics_duration_milliseconds_bucket[5m])) by (le))",
          "legendFormat": "P50",
          "refId": "A"
        },
        {
          "datasource": { "type": "prometheus", "uid": "prometheus" },
          "expr": "histogram_quantile(0.95, sum(rate(traces_spanmetrics_duration_milliseconds_bucket[5m])) by (le))",
          "legendFormat": "P95",
          "refId": "B"
        },
        {
          "datasource": { "type": "prometheus", "uid": "prometheus" },
          "expr": "histogram_quantile(0.99, sum(rate(traces_spanmetrics_duration_milliseconds_bucket[5m])) by (le))",
          "legendFormat": "P99",
          "refId": "C"
        }
      ]
    },
    {
      "collapsed": false,
      "gridPos": { "h": 1, "w": 24, "x": 0, "y": 14 },
      "id": 7,
      "title": "Business Metrics",
      "type": "row"
    },
    {
      "datasource": { "type": "prometheus", "uid": "prometheus" },
      "description": "Current number of active parking reservations",
      "fieldConfig": {
        "defaults": {
          "color": { "mode": "thresholds" },
          "mappings": [],
          "thresholds": {
            "mode": "absolute",
            "steps": [
              { "color": "green", "value": null },
              { "color": "yellow", "value": 500 },
              { "color": "red", "value": 1000 }
            ]
          },
          "unit": "short"
        },
        "overrides": []
      },
      "gridPos": { "h": 6, "w": 6, "x": 0, "y": 15 },
      "id": 8,
      "options": {
        "orientation": "auto",
        "reduceOptions": { "calcs": ["lastNotNull"], "fields": "", "values": false },
        "showThresholdLabels": false,
        "showThresholdMarkers": true
      },
      "title": "Active Reservations",
      "type": "gauge",
      "targets": [
        {
          "datasource": { "type": "prometheus", "uid": "prometheus" },
          "expr": "sum(active_reservations) or vector(0)",
          "legendFormat": "Active",
          "refId": "A"
        }
      ]
    },
    {
      "datasource": { "type": "prometheus", "uid": "prometheus" },
      "description": "NATS consumer lag: difference between published and consumed message rates",
      "fieldConfig": {
        "defaults": {
          "color": { "mode": "palette-classic" },
          "custom": {
            "axisBorderShow": false,
            "axisCenteredZero": false,
            "axisColorMode": "text",
            "axisLabel": "msg/s lag",
            "axisPlacement": "auto",
            "barAlignment": 0,
            "drawStyle": "line",
            "fillOpacity": 15,
            "gradientMode": "none",
            "hideFrom": { "legend": false, "tooltip": false, "viz": false },
            "insertNulls": false,
            "lineInterpolation": "smooth",
            "lineWidth": 2,
            "pointSize": 5,
            "scaleDistribution": { "type": "linear" },
            "showPoints": "never",
            "spanNulls": false,
            "stacking": { "group": "A", "mode": "none" },
            "thresholdsStyle": { "mode": "line+area" }
          },
          "mappings": [],
          "thresholds": {
            "mode": "absolute",
            "steps": [
              { "color": "transparent", "value": null },
              { "color": "red", "value": 100 }
            ]
          },
          "unit": "short"
        },
        "overrides": []
      },
      "gridPos": { "h": 6, "w": 6, "x": 6, "y": 15 },
      "id": 9,
      "options": {
        "legend": { "calcs": ["mean", "max"], "displayMode": "table", "placement": "bottom", "showLegend": true },
        "tooltip": { "mode": "multi", "sort": "desc" }
      },
      "title": "NATS Consumer Lag",
      "type": "timeseries",
      "targets": [
        {
          "datasource": { "type": "prometheus", "uid": "prometheus" },
          "expr": "rate(nats_messages_published_total[5m]) - rate(nats_messages_consumed_total[5m])",
          "legendFormat": "{{job}}",
          "refId": "A"
        }
      ]
    },
    {
      "datasource": { "type": "prometheus", "uid": "prometheus" },
      "description": "Database connection pool: active vs idle vs max connections",
      "fieldConfig": {
        "defaults": {
          "color": { "mode": "palette-classic" },
          "custom": {
            "axisBorderShow": false,
            "axisCenteredZero": false,
            "axisColorMode": "text",
            "axisLabel": "",
            "axisPlacement": "auto",
            "barAlignment": 0,
            "drawStyle": "line",
            "fillOpacity": 15,
            "gradientMode": "none",
            "hideFrom": { "legend": false, "tooltip": false, "viz": false },
            "insertNulls": false,
            "lineInterpolation": "smooth",
            "lineWidth": 2,
            "pointSize": 5,
            "scaleDistribution": { "type": "linear" },
            "showPoints": "never",
            "spanNulls": false,
            "stacking": { "group": "A", "mode": "none" },
            "thresholdsStyle": { "mode": "off" }
          },
          "mappings": [],
          "thresholds": {
            "mode": "absolute",
            "steps": [
              { "color": "green", "value": null }
            ]
          },
          "unit": "short"
        },
        "overrides": []
      },
      "gridPos": { "h": 6, "w": 6, "x": 12, "y": 15 },
      "id": 10,
      "options": {
        "legend": { "calcs": ["mean", "lastNotNull"], "displayMode": "table", "placement": "bottom", "showLegend": true },
        "tooltip": { "mode": "multi", "sort": "desc" }
      },
      "title": "Database Connection Pool",
      "type": "timeseries",
      "targets": [
        {
          "datasource": { "type": "prometheus", "uid": "prometheus" },
          "expr": "sum(db_pool_active_connections) by (job)",
          "legendFormat": "active {{job}}",
          "refId": "A"
        },
        {
          "datasource": { "type": "prometheus", "uid": "prometheus" },
          "expr": "sum(db_pool_idle_connections) by (job)",
          "legendFormat": "idle {{job}}",
          "refId": "B"
        },
        {
          "datasource": { "type": "prometheus", "uid": "prometheus" },
          "expr": "sum(db_pool_max_connections) by (job)",
          "legendFormat": "max {{job}}",
          "refId": "C"
        }
      ]
    },
    {
      "datasource": { "type": "prometheus", "uid": "prometheus" },
      "description": "Redis memory usage across instances",
      "fieldConfig": {
        "defaults": {
          "color": { "mode": "palette-classic" },
          "custom": {
            "axisBorderShow": false,
            "axisCenteredZero": false,
            "axisColorMode": "text",
            "axisLabel": "",
            "axisPlacement": "auto",
            "barAlignment": 0,
            "drawStyle": "line",
            "fillOpacity": 15,
            "gradientMode": "none",
            "hideFrom": { "legend": false, "tooltip": false, "viz": false },
            "insertNulls": false,
            "lineInterpolation": "smooth",
            "lineWidth": 2,
            "pointSize": 5,
            "scaleDistribution": { "type": "linear" },
            "showPoints": "never",
            "spanNulls": false,
            "stacking": { "group": "A", "mode": "none" },
            "thresholdsStyle": { "mode": "off" }
          },
          "mappings": [],
          "thresholds": {
            "mode": "absolute",
            "steps": [
              { "color": "green", "value": null }
            ]
          },
          "unit": "bytes"
        },
        "overrides": []
      },
      "gridPos": { "h": 6, "w": 6, "x": 18, "y": 15 },
      "id": 11,
      "options": {
        "legend": { "calcs": ["mean", "lastNotNull"], "displayMode": "table", "placement": "bottom", "showLegend": true },
        "tooltip": { "mode": "multi", "sort": "desc" }
      },
      "title": "Redis Memory Usage",
      "type": "timeseries",
      "targets": [
        {
          "datasource": { "type": "prometheus", "uid": "prometheus" },
          "expr": "redis_memory_used_bytes",
          "legendFormat": "used {{instance}}",
          "refId": "A"
        },
        {
          "datasource": { "type": "prometheus", "uid": "prometheus" },
          "expr": "redis_memory_max_bytes",
          "legendFormat": "max {{instance}}",
          "refId": "B"
        }
      ]
    }
  ],
  "schemaVersion": 39,
  "tags": ["parkir-pintar", "overview", "RED", "infrastructure"],
  "templating": { "list": [] },
  "time": { "from": "now-1h", "to": "now" },
  "timepicker": {},
  "timezone": "browser",
  "title": "ParkirPintar - Overview",
  "uid": "parkir-pintar-overview",
  "version": 1,
  "weekStart": ""
}
